explauto/__init__.py
explauto/_version.py
explauto/exceptions.py
explauto/agent/__init__.py
explauto/agent/agent.py
explauto/environment/__init__.py
explauto/environment/context_environment.py
explauto/environment/environment.py
explauto/environment/testcase.py
explauto/environment/diva/__init__.py
explauto/environment/diva/config.py
explauto/environment/diva/diva.py
explauto/environment/npendulum/__init__.py
explauto/environment/npendulum/npendulum.py
explauto/environment/npendulum/simulation.py
explauto/environment/pendulum/__init__.py
explauto/environment/pendulum/config.py
explauto/environment/pendulum/generate_simple_lip.py
explauto/environment/pendulum/pendulum.py
explauto/environment/pendulum/simple_lip.py
explauto/environment/poppy/__init__.py
explauto/environment/poppy/poppy_env.py
explauto/environment/simple_arm/__init__.py
explauto/environment/simple_arm/simple_arm.py
explauto/environment/toys/__init__.py
explauto/environment/toys/discrete_1d_progress.py
explauto/environment/toys/hierarchical_mild.py
explauto/evaluation/__init__.py
explauto/evaluation/evaluation.py
explauto/experiment/__init__.py
explauto/experiment/experiment.py
explauto/experiment/log.py
explauto/experiment/pool.py
explauto/interest_model/__init__.py
explauto/interest_model/competences.py
explauto/interest_model/discrete_progress.py
explauto/interest_model/gmm_progress.py
explauto/interest_model/interest_model.py
explauto/interest_model/mouse_pointer.py
explauto/interest_model/random.py
explauto/interest_model/tree.py
explauto/io/__init__.py
explauto/io/mouse_pointer.py
explauto/models/__init__.py
explauto/models/dataset.py
explauto/models/dmp.py
explauto/models/gaussian.py
explauto/models/gmminf.py
explauto/models/imle_model.py
explauto/models/motor_primitive.py
explauto/models/tests.py
explauto/sensorimotor_model/__init__.py
explauto/sensorimotor_model/ilo_gmm.py
explauto/sensorimotor_model/imle.py
explauto-1.2.0.dist-info/DESCRIPTION.rst
explauto-1.2.0.dist-info/METADATA
explauto-1.2.0.dist-info/RECORD
explauto-1.2.0.dist-info/WHEEL
explauto-1.2.0.dist-info/metadata.json
explauto-1.2.0.dist-info/top_level.txt
explauto-1.2.0.dist-info/zip-safe
