Metadata-Version: 2.0
Name: explauto
Version: 1.2.0
Summary: Python Library for Autonomous Exploration
Home-page: https://github.com/flowersteam/explauto
Author: Clement Moulin-Frier, Pierre Rouanet
Author-email: clement.moulinfrier@gmail.com
License: GNU GENERAL PUBLIC LICENSE Version 3
Platform: UNKNOWN
Requires-Dist: numpy
Requires-Dist: scikit-learn
Requires-Dist: scipy
